MANIFEST.in
README.rst
setup_accel.py
versiontools_support.py
skl_groups_accel/__init__.py
skl_groups_accel/knn_divs.c
skl_groups_accel.egg-info/PKG-INFO
skl_groups_accel.egg-info/SOURCES.txt
skl_groups_accel.egg-info/dependency_links.txt
skl_groups_accel.egg-info/not-zip-safe
skl_groups_accel.egg-info/pbr.json
skl_groups_accel.egg-info/requires.txt
skl_groups_accel.egg-info/top_level.txt