Metadata-Version: 1.1
Name: skl-groups-accel
Version: 0.1.6
Summary: Compiled components to speed up skl-groups.
Home-page: https://github.com/dougalsutherland/skl-groups-accel
Author: Dougal J. Sutherland
Author-email: dsutherl@cs.cmu.edu
License: BSD
Download-URL: https://github.com/dougalsutherland/skl-groups-accel
Platform: UNKNOWN
Classifier: Development Status :: 2 - Pre-Alpha
Classifier: Intended Audience :: Science/Research
Classifier: License :: OSI Approved :: BSD License
Classifier: Operating System :: OS Independent
Classifier: Programming Language :: Python :: 2
Classifier: Programming Language :: Python :: 2.7
Classifier: Programming Language :: Python :: 3
Classifier: Programming Language :: Python :: 3.3
Classifier: Programming Language :: Python :: 3.4
Classifier: Programming Language :: Python :: Implementation :: CPython
Classifier: Topic :: Scientific/Engineering :: Artificial Intelligence
Classifier: Topic :: Scientific/Engineering :: Image Recognition
Classifier: Topic :: Scientific/Engineering :: Information Analysis
